LICENSE
MANIFEST.in
README.rst
setup.cfg
setup.py
conf/config.py
conf/squid.conf
freehp/__init__.py
freehp/_patch.py
freehp/checker.py
freehp/cli.py
freehp/commands.py
freehp/config.py
freehp/errors.py
freehp/extractor.py
freehp/manager.py
freehp/spider.py
freehp/squid.py
freehp/utils.py
freehp/version.py
freehp.egg-info/PKG-INFO
freehp.egg-info/SOURCES.txt
freehp.egg-info/dependency_links.txt
freehp.egg-info/entry_points.txt
freehp.egg-info/not-zip-safe
freehp.egg-info/requires.txt
freehp.egg-info/top_level.txt
tests/__init__.py
tests/test_checker.py
tests/test_extractor.py