Metadata-Version: 1.1
Name: freehp
Version: 0.4.3
Summary: Providing Free HTTP proxies
Home-page: https://github.com/jadbin/freehp
Author: jadbin
Author-email: jadbin.com@hotmail.com
License: Apache 2
Platform: UNKNOWN
Classifier: License :: OSI Approved :: Apache Software License
Classifier: Intended Audience :: Developers
Classifier: Programming Language :: Python
Classifier: Programming Language :: Python :: 3
Classifier: Programming Language :: Python :: 3.5
Classifier: Topic :: Internet :: WWW/HTTP
